odoo/addons/purchase_stock_viewer/__init__.py
odoo/addons/purchase_stock_viewer/__manifest__.py
odoo/addons/purchase_stock_viewer/security/ir.model.access.csv
odoo/addons/purchase_stock_viewer/static/description/icon.png
odoo12_addon_purchase_stock_viewer-12.0.1.0.0.99.dev2.dist-info/METADATA
odoo12_addon_purchase_stock_viewer-12.0.1.0.0.99.dev2.dist-info/WHEEL
odoo12_addon_purchase_stock_viewer-12.0.1.0.0.99.dev2.dist-info/top_level.txt
odoo12_addon_purchase_stock_viewer-12.0.1.0.0.99.dev2.dist-info/RECORD
