Metadata-Version: 2.1
Name: odoo12-addon-purchase_stock_viewer
Version: 12.0.1.0.0.99.dev2
Requires-Python: >=3.5
Requires-Dist: odoo12-addon-purchase_viewer
Requires-Dist: odoo>=12.0a,<12.1dev
Summary: Adds a group 'Purchase viewer'
Home-page: http://www.akretion.com
License: AGPL-3
Author: Akretion
Classifier: Programming Language :: Python
Classifier: Framework :: Odoo
Classifier: Framework :: Odoo :: 12.0
Classifier: License :: OSI Approved :: GNU Affero General Public License v3
